pyrootfinder/__init__.py
pyrootfinder/exceptions.py
pyrootfinder/result.py
pyrootfinder/solvers.py
pyrootfinder-0.1.1.dist-info/licenses/LICENSE
pyrootfinder-0.1.1.dist-info/METADATA
pyrootfinder-0.1.1.dist-info/WHEEL
pyrootfinder-0.1.1.dist-info/top_level.txt
pyrootfinder-0.1.1.dist-info/RECORD
