Metadata-Version: 2.4
Name: pyrootfinder
Version: 0.1.1
Summary: A clean, robust, and easy-to-use Python package for finding roots of equations using multiple numerical algorithms.
Author-email: Sanjay Choudhary <sanjay@mailchat.me>
License: MIT License
Project-URL: Homepage, https://github.com/cu-sanjay/pyrootfinder
Project-URL: Repository, https://github.com/cu-sanjay/pyrootfinder
Project-URL: Issues, https://github.com/cu-sanjay/pyrootfinder/issues
Project-URL: Documentation, https://github.com/cu-sanjay/pyrootfinder#readme
Keywords: root finding,numerical methods,solver,newton,bisection,brentq,secant,halley,equation
Classifier: Development Status :: 5 - Production/Stable
Classifier: Intended Audience :: Developers
Classifier: Intended Audience :: Science/Research
Classifier: License :: OSI Approved :: MIT License
Classifier: Operating System :: OS Independent
Classifier: Programming Language :: Python :: 3
Classifier: Programming Language :: Python :: 3.8
Classifier: Programming Language :: Python :: 3.9
Classifier: Programming Language :: Python :: 3.10
Classifier: Programming Language :: Python :: 3.11
Classifier: Topic :: Software Development :: Libraries :: Python Modules
Classifier: Topic :: Scientific/Engineering :: Mathematics
Requires-Python: >=3.8
License-File: LICENSE
Dynamic: license-file
